MANIFEST.in
setup.cfg
setup.py
stratus_api/syndication/__init__.py
stratus_api/syndication/base.py
stratus_api/syndication/schemas/v1.yaml
stratus_api_syndication.egg-info/PKG-INFO
stratus_api_syndication.egg-info/SOURCES.txt
stratus_api_syndication.egg-info/dependency_links.txt
stratus_api_syndication.egg-info/requires.txt
stratus_api_syndication.egg-info/top_level.txt