Metadata-Version: 2.1
Name: stratus-api-syndication
Version: 0.0.5
Summary: Streamlined Data Syndication
Home-page: https://bitbucket.org/adarainc/stratus-api-syndication
Author: DOT
Author-email: dot@adara.com
License: UNKNOWN
Platform: UNKNOWN
Classifier: Programming Language :: Python :: 3
Classifier: License :: OSI Approved :: MIT License
Classifier: Operating System :: OS Independent
Requires-Python: >=3.11
